feature_gen/__init__.py
feature_gen/feature_gen_master.py
feature_gen/implementation/__init__.py
feature_gen/implementation/constants.py
feature_gen/implementation/ensemble_classifier.py
feature_gen/implementation/get_the_most_optimal_features_set.py
feature_gen/implementation/msga_2/__init__.py
feature_gen/implementation/msga_2/nsga2_algorithm.py
feature_gen/utils/__init__.py
feature_gen/utils/checker.py
feature_gen/utils/df_preprocessor.py
feature_gen-0.1.4.dist-info/METADATA
feature_gen-0.1.4.dist-info/WHEEL
feature_gen-0.1.4.dist-info/top_level.txt
feature_gen-0.1.4.dist-info/RECORD
